{
  "daily": {
    "2026-07-09": {
      "cost": 3.064345949982,
      "traces": 11,
      "users": 3
    },
    "2026-07-10": {
      "cost": 4.3807055999780005,
      "traces": 10,
      "users": 4
    },
    "2026-07-13": {
      "cost": 0.22760475000000002,
      "traces": 3,
      "users": 2
    },
    "2026-07-14": {
      "cost": 29.983287849912998,
      "traces": 41,
      "users": 3
    },
    "2026-07-15": {
      "cost": 12.194030249923001,
      "traces": 37,
      "users": 5
    },
    "2026-07-16": {
      "cost": 12.219764049932,
      "traces": 36,
      "users": 3
    },
    "2026-07-17": {
      "cost": 69.91950699977801,
      "traces": 75,
      "users": 4
    },
    "2026-07-20": {
      "cost": 25.309307999902,
      "traces": 32,
      "users": 2
    }
  },
  "snapshots": {
    "last24hours": {
      "updated_at": "2026-07-20T10:48:41+05:30",
      "users": [
        {
          "cost": 19.506445199927,
          "email": "geethu.gs@accenture.com",
          "traces": 27,
          "url": "https://ai-logs.wavemakeronline.com/project/d9a447c5-c224-48c4-9370-f3fc0bae3466/users/prod-ai_acn-onboarding_geethu.gs@accenture.com"
        },
        {
          "cost": 5.802862799975,
          "email": "kaustab.das@accenture.com",
          "traces": 5,
          "url": "https://ai-logs.wavemakeronline.com/project/d9a447c5-c224-48c4-9370-f3fc0bae3466/users/prod-ai_acn-onboarding_kaustab.das@accenture.com"
        }
      ],
      "window_days": 1
    },
    "last30days": {
      "updated_at": "2026-07-20T10:48:41+05:30",
      "users": [
        {
          "cost": 87.977728299712,
          "email": "kaustab.das@accenture.com",
          "traces": 82,
          "url": "https://ai-logs.wavemakeronline.com/project/d9a447c5-c224-48c4-9370-f3fc0bae3466/users/prod-ai_acn-onboarding_kaustab.das@accenture.com"
        },
        {
          "cost": 72.189680099724,
          "email": "geethu.gs@accenture.com",
          "traces": 124,
          "url": "https://ai-logs.wavemakeronline.com/project/d9a447c5-c224-48c4-9370-f3fc0bae3466/users/prod-ai_acn-onboarding_geethu.gs@accenture.com"
        },
        {
          "cost": 43.697169699821,
          "email": "dhanya.b.rao@accenture.com",
          "traces": 101,
          "url": "https://ai-logs.wavemakeronline.com/project/d9a447c5-c224-48c4-9370-f3fc0bae3466/users/prod-ai_acn-onboarding_dhanya.b.rao@accenture.com"
        },
        {
          "cost": 30.403055749862,
          "email": "sameer.a.b.kulkarni@accenture.com",
          "traces": 41,
          "url": "https://ai-logs.wavemakeronline.com/project/d9a447c5-c224-48c4-9370-f3fc0bae3466/users/prod-ai_acn-onboarding_sameer.a.b.kulkarni@accenture.com"
        },
        {
          "cost": 29.950730249901,
          "email": "prince.t.jacob@accenture.com",
          "traces": 45,
          "url": "https://ai-logs.wavemakeronline.com/project/d9a447c5-c224-48c4-9370-f3fc0bae3466/users/prod-ai_acn-onboarding_prince.t.jacob@accenture.com"
        },
        {
          "cost": 3.70360394998,
          "email": "priyanka.bhadri@wavemaker.com",
          "traces": 13,
          "url": "https://ai-logs.wavemakeronline.com/project/d9a447c5-c224-48c4-9370-f3fc0bae3466/users/prod-ai_acn-onboarding_priyanka.bhadri@wavemaker.com"
        }
      ],
      "window_days": 30
    }
  }
}
